{
    "@Redfish.Settings": {
        "@odata.context": "/redfish/v1/$metadata#Settings.Settings",
        "@odata.type": "#Settings.v1_1_0.Settings",
        "SettingsObject": {
            "@odata.id": "/redfish/v1/Managers/System.Embedded.1/Attributes/Settings"
        },
        "SupportedApplyTimes": [
            "Immediate",
            "AtMaintenanceWindowStart"
        ]
    },
    "@odata.context": "/redfish/v1/$metadata#DellAttributes.DellAttributes",
    "@odata.id": "/redfish/v1/Managers/System.Embedded.1/Attributes",
    "@odata.type": "#DellAttributes.v1_0_0.DellAttributes",
    "AttributeRegistry": "ManagerAttributeRegistry.v1_0_0",
    "Attributes": {
        "AcquisitionInfo.1.CostCenter": "",
        "AcquisitionInfo.1.Expensed": "No",
        "AcquisitionInfo.1.InstallDate": "",
        "AcquisitionInfo.1.PONumber": "0",
        "AcquisitionInfo.1.PurchaseCost": "0",
        "AcquisitionInfo.1.PurchaseDate": "",
        "AcquisitionInfo.1.Vendor": "Dell",
        "AcquisitionInfo.1.WayBill": "0",
        "AcquisitionInfo.1.WhoSigned": "",
        "Backplane.1.BackplaneBusMode": "I2C",
        "Backplane.1.BackplaneSplitMode": 0,
        "ChassisInfo.1.ChassisModel": "PowerEdge M1000e",
        "ChassisInfo.1.ChassisName": "CMC-51F3DK2",
        "ChassisInfo.1.ChassisServiceTag": "51F3DK2",
        "ChassisInfo.1.ChassisType": "M1000e",
        "ChassisInfo.1.ConnectionState": "Connected/Ready",
        "ChassisInfo.1.FirmwareVersion": "6.20",
        "ChassisInfo.1.IPV4Address": "10.193.251.36",
        "ChassisInfo.1.IPV6Address": "",
        "CustomAsset.1.Label": "",
        "CustomAsset.1.Value": "",
        "CustomAsset.10.Label": "",
        "CustomAsset.10.Value": "",
        "CustomAsset.11.Label": "",
        "CustomAsset.11.Value": "",
        "CustomAsset.12.Label": "",
        "CustomAsset.12.Value": "",
        "CustomAsset.13.Label": "",
        "CustomAsset.13.Value": "",
        "CustomAsset.14.Label": "",
        "CustomAsset.14.Value": "",
        "CustomAsset.15.Label": "",
        "CustomAsset.15.Value": "",
        "CustomAsset.16.Label": "",
        "CustomAsset.16.Value": "",
        "CustomAsset.17.Label": "",
        "CustomAsset.17.Value": "",
        "CustomAsset.18.Label": "",
        "CustomAsset.18.Value": "",
        "CustomAsset.19.Label": "",
        "CustomAsset.19.Value": "",
        "CustomAsset.2.Label": "",
        "CustomAsset.2.Value": "",
        "CustomAsset.20.Label": "",
        "CustomAsset.20.Value": "",
        "CustomAsset.21.Label": "",
        "CustomAsset.21.Value": "",
        "CustomAsset.22.Label": "",
        "CustomAsset.22.Value": "",
        "CustomAsset.23.Label": "",
        "CustomAsset.23.Value": "",
        "CustomAsset.24.Label": "",
        "CustomAsset.24.Value": "",
        "CustomAsset.25.Label": "",
        "CustomAsset.25.Value": "",
        "CustomAsset.26.Label": "",
        "CustomAsset.26.Value": "",
        "CustomAsset.27.Label": "",
        "CustomAsset.27.Value": "",
        "CustomAsset.28.Label": "",
        "CustomAsset.28.Value": "",
        "CustomAsset.29.Label": "",
        "CustomAsset.29.Value": "",
        "CustomAsset.3.Label": "",
        "CustomAsset.3.Value": "",
        "CustomAsset.30.Label": "",
        "CustomAsset.30.Value": "",
        "CustomAsset.31.Label": "",
        "CustomAsset.31.Value": "",
        "CustomAsset.32.Label": "",
        "CustomAsset.32.Value": "",
        "CustomAsset.4.Label": "",
        "CustomAsset.4.Value": "",
        "CustomAsset.5.Label": "",
        "CustomAsset.5.Value": "",
        "CustomAsset.6.Label": "",
        "CustomAsset.6.Value": "",
        "CustomAsset.7.Label": "",
        "CustomAsset.7.Value": "",
        "CustomAsset.8.Label": "",
        "CustomAsset.8.Value": "",
        "CustomAsset.9.Label": "",
        "CustomAsset.9.Value": "",
        "DepreciationInfo.1.Duration": "0",
        "DepreciationInfo.1.DurationUnit": "Months",
        "DepreciationInfo.1.Method": "",
        "DepreciationInfo.1.Percentage": "0",
        "Diagnostics.1.OSAppCollectionTime": "N/A",
        "ExtWarrantyInfo.1.Cost": "0",
        "ExtWarrantyInfo.1.EndDate": "",
        "ExtWarrantyInfo.1.Provider": "",
        "ExtWarrantyInfo.1.StartDate": "",
        "LCD.1.ChassisIdentifyDuration": 0,
        "LeaseInfo.1.Buyout": "0",
        "LeaseInfo.1.EndDate": "",
        "LeaseInfo.1.FairValue": "0",
        "LeaseInfo.1.Lessor": "",
        "LeaseInfo.1.MultiSched": "No",
        "LeaseInfo.1.RateFactor": "0",
        "MaintenanceInfo.1.EndDate": "",
        "MaintenanceInfo.1.Provider": "",
        "MaintenanceInfo.1.Restrictions": "",
        "MaintenanceInfo.1.StartDate": "",
        "OutsourceInfo.1.ProbComp": "",
        "OutsourceInfo.1.ProviderFee": "0",
        "OutsourceInfo.1.SLALevel": "",
        "OutsourceInfo.1.ServiceFee": "0",
        "OutsourceInfo.1.SignedFor": "",
        "OwnerInfo.1.InsComp": "",
        "OwnerInfo.1.OwnerName": "",
        "OwnerInfo.1.Type": "Owned",
        "PCIeSlotLFM.1.3rdPartyCard": "N/A",
        "PCIeSlotLFM.1.CardType": "Empty",
        "PCIeSlotLFM.1.CustomLFM": 0,
        "PCIeSlotLFM.1.LFMMode": "Automatic",
        "PCIeSlotLFM.1.MaxLFM": 0,
        "PCIeSlotLFM.1.PCIeInletTemperature": 0,
        "PCIeSlotLFM.1.SlotState": "Defined",
        "PCIeSlotLFM.1.TargetLFM": "-",
        "PCIeSlotLFM.10.3rdPartyCard": "N/A",
        "PCIeSlotLFM.10.CardType": "Empty",
        "PCIeSlotLFM.10.CustomLFM": 0,
        "PCIeSlotLFM.10.LFMMode": "Automatic",
        "PCIeSlotLFM.10.MaxLFM": 0,
        "PCIeSlotLFM.10.PCIeInletTemperature": 0,
        "PCIeSlotLFM.10.SlotState": "Not-Defined",
        "PCIeSlotLFM.10.TargetLFM": "-",
        "PCIeSlotLFM.11.3rdPartyCard": "N/A",
        "PCIeSlotLFM.11.CardType": "Empty",
        "PCIeSlotLFM.11.CustomLFM": 0,
        "PCIeSlotLFM.11.LFMMode": "Automatic",
        "PCIeSlotLFM.11.MaxLFM": 0,
        "PCIeSlotLFM.11.PCIeInletTemperature": 0,
        "PCIeSlotLFM.11.SlotState": "Not-Defined",
        "PCIeSlotLFM.11.TargetLFM": "-",
        "PCIeSlotLFM.12.3rdPartyCard": "N/A",
        "PCIeSlotLFM.12.CardType": "Empty",
        "PCIeSlotLFM.12.CustomLFM": 0,
        "PCIeSlotLFM.12.LFMMode": "Automatic",
        "PCIeSlotLFM.12.MaxLFM": 0,
        "PCIeSlotLFM.12.PCIeInletTemperature": 0,
        "PCIeSlotLFM.12.SlotState": "Not-Defined",
        "PCIeSlotLFM.12.TargetLFM": "-",
        "PCIeSlotLFM.13.3rdPartyCard": "N/A",
        "PCIeSlotLFM.13.CardType": "Empty",
        "PCIeSlotLFM.13.CustomLFM": 0,
        "PCIeSlotLFM.13.LFMMode": "Automatic",
        "PCIeSlotLFM.13.MaxLFM": 0,
        "PCIeSlotLFM.13.PCIeInletTemperature": 0,
        "PCIeSlotLFM.13.SlotState": "Not-Defined",
        "PCIeSlotLFM.13.TargetLFM": "-",
        "PCIeSlotLFM.14.3rdPartyCard": "N/A",
        "PCIeSlotLFM.14.CardType": "Empty",
        "PCIeSlotLFM.14.CustomLFM": 0,
        "PCIeSlotLFM.14.LFMMode": "Automatic",
        "PCIeSlotLFM.14.MaxLFM": 0,
        "PCIeSlotLFM.14.PCIeInletTemperature": 0,
        "PCIeSlotLFM.14.SlotState": "Not-Defined",
        "PCIeSlotLFM.14.TargetLFM": "-",
        "PCIeSlotLFM.15.3rdPartyCard": "N/A",
        "PCIeSlotLFM.15.CardType": "Empty",
        "PCIeSlotLFM.15.CustomLFM": 0,
        "PCIeSlotLFM.15.LFMMode": "Automatic",
        "PCIeSlotLFM.15.MaxLFM": 0,
        "PCIeSlotLFM.15.PCIeInletTemperature": 0,
        "PCIeSlotLFM.15.SlotState": "Not-Defined",
        "PCIeSlotLFM.15.TargetLFM": "-",
        "PCIeSlotLFM.2.3rdPartyCard": "N/A",
        "PCIeSlotLFM.2.CardType": "Empty",
        "PCIeSlotLFM.2.CustomLFM": 0,
        "PCIeSlotLFM.2.LFMMode": "Automatic",
        "PCIeSlotLFM.2.MaxLFM": 0,
        "PCIeSlotLFM.2.PCIeInletTemperature": 0,
        "PCIeSlotLFM.2.SlotState": "Defined",
        "PCIeSlotLFM.2.TargetLFM": "-",
        "PCIeSlotLFM.3.3rdPartyCard": "N/A",
        "PCIeSlotLFM.3.CardType": "Empty",
        "PCIeSlotLFM.3.CustomLFM": 0,
        "PCIeSlotLFM.3.LFMMode": "Automatic",
        "PCIeSlotLFM.3.MaxLFM": 0,
        "PCIeSlotLFM.3.PCIeInletTemperature": 0,
        "PCIeSlotLFM.3.SlotState": "Not-Defined",
        "PCIeSlotLFM.3.TargetLFM": "-",
        "PCIeSlotLFM.4.3rdPartyCard": "N/A",
        "PCIeSlotLFM.4.CardType": "Empty",
        "PCIeSlotLFM.4.CustomLFM": 0,
        "PCIeSlotLFM.4.LFMMode": "Automatic",
        "PCIeSlotLFM.4.MaxLFM": 0,
        "PCIeSlotLFM.4.PCIeInletTemperature": 0,
        "PCIeSlotLFM.4.SlotState": "Not-Defined",
        "PCIeSlotLFM.4.TargetLFM": "-",
        "PCIeSlotLFM.5.3rdPartyCard": "N/A",
        "PCIeSlotLFM.5.CardType": "Empty",
        "PCIeSlotLFM.5.CustomLFM": 0,
        "PCIeSlotLFM.5.LFMMode": "Automatic",
        "PCIeSlotLFM.5.MaxLFM": 0,
        "PCIeSlotLFM.5.PCIeInletTemperature": 0,
        "PCIeSlotLFM.5.SlotState": "Not-Defined",
        "PCIeSlotLFM.5.TargetLFM": "-",
        "PCIeSlotLFM.6.3rdPartyCard": "N/A",
        "PCIeSlotLFM.6.CardType": "Empty",
        "PCIeSlotLFM.6.CustomLFM": 0,
        "PCIeSlotLFM.6.LFMMode": "Automatic",
        "PCIeSlotLFM.6.MaxLFM": 0,
        "PCIeSlotLFM.6.PCIeInletTemperature": 0,
        "PCIeSlotLFM.6.SlotState": "Not-Defined",
        "PCIeSlotLFM.6.TargetLFM": "-",
        "PCIeSlotLFM.7.3rdPartyCard": "N/A",
        "PCIeSlotLFM.7.CardType": "Empty",
        "PCIeSlotLFM.7.CustomLFM": 0,
        "PCIeSlotLFM.7.LFMMode": "Automatic",
        "PCIeSlotLFM.7.MaxLFM": 0,
        "PCIeSlotLFM.7.PCIeInletTemperature": 0,
        "PCIeSlotLFM.7.SlotState": "Not-Defined",
        "PCIeSlotLFM.7.TargetLFM": "-",
        "PCIeSlotLFM.8.3rdPartyCard": "N/A",
        "PCIeSlotLFM.8.CardType": "Empty",
        "PCIeSlotLFM.8.CustomLFM": 0,
        "PCIeSlotLFM.8.LFMMode": "Automatic",
        "PCIeSlotLFM.8.MaxLFM": 0,
        "PCIeSlotLFM.8.PCIeInletTemperature": 0,
        "PCIeSlotLFM.8.SlotState": "Not-Defined",
        "PCIeSlotLFM.8.TargetLFM": "-",
        "PCIeSlotLFM.9.3rdPartyCard": "N/A",
        "PCIeSlotLFM.9.CardType": "Empty",
        "PCIeSlotLFM.9.CustomLFM": 0,
        "PCIeSlotLFM.9.LFMMode": "Automatic",
        "PCIeSlotLFM.9.MaxLFM": 0,
        "PCIeSlotLFM.9.PCIeInletTemperature": 0,
        "PCIeSlotLFM.9.SlotState": "Not-Defined",
        "PCIeSlotLFM.9.TargetLFM": "-",
        "PowerHistorical.1.IntervalInSeconds": 0,
        "SC-BMC.1.PowerMonitoring": 0,
        "ServerInfo.1.NodeID": "FOOBAZ",
        "ServerInfo.1.RChassisServiceTag": "",
        "ServerInfo.1.ServerType": "Blade",
        "ServerInfo.1.ServiceTag": "FOOBAZ",
        "ServerOS.1.HostName": "graphite-1503.ams4.prod.example.com",
        "ServerOS.1.OEMOSVersion": "",
        "ServerOS.1.OSName": "",
        "ServerOS.1.OSVersion": "",
        "ServerOS.1.ProductKey": "",
        "ServerOS.1.ServerPoweredOnTime": 0,
        "ServerPwr.1.ActivePolicyName": "",
        "ServerPwr.1.ActivePowerCapVal": 32767,
        "ServerPwr.1.PowerCapMaxThres": 334,
        "ServerPwr.1.PowerCapMinThres": 204,
        "ServerPwr.1.PowerCapSetting": "Disabled",
        "ServerPwr.1.PowerCapValue": 32767,
        "ServerPwrMon.1.AccumulativePower": 1669820,
        "ServerPwrMon.1.CumulativePowerStartTime": 1509372216,
        "ServerPwrMon.1.CumulativePowerStartTimeStr": "0",
        "ServerPwrMon.1.MinPowerTime": 1559258577,
        "ServerPwrMon.1.MinPowerTimeStr": "2019-05-30T23:22:57Z",
        "ServerPwrMon.1.MinPowerWatts": 8,
        "ServerPwrMon.1.PeakCurrentTime": 1509377114,
        "ServerPwrMon.1.PeakCurrentTimeStr": "0",
        "ServerPwrMon.1.PeakPowerStartTime": 1509372216,
        "ServerPwrMon.1.PeakPowerStartTimeStr": "0",
        "ServerPwrMon.1.PeakPowerTime": 1509377114,
        "ServerPwrMon.1.PeakPowerTimeStr": "0",
        "ServerPwrMon.1.PeakPowerWatts": 213,
        "ServerPwrMon.1.PowerConfigReset": "None",
        "ServerTopology.1.AisleName": "",
        "ServerTopology.1.BladeSlotNumInChassis": "5",
        "ServerTopology.1.ChassisName": "CMC-51F3DK2",
        "ServerTopology.1.DataCenterName": "",
        "ServerTopology.1.RackName": "",
        "ServerTopology.1.RackSlot": 1,
        "ServerTopology.1.RoomName": "",
        "ServerTopology.1.SizeOfManagedSystemInU": 10,
        "ServiceContract.1.Renewed": "No",
        "ServiceContract.1.Type": "",
        "ServiceContract.1.Vendor": "",
        "Storage.1.AvailableSpareAlertThreshold": 10,
        "Storage.1.RemainingRatedWriteEnduranceAlertThreshold": 10,
        "SupportInfo.1.AutoFix": "",
        "SupportInfo.1.HelpDesk": "",
        "SupportInfo.1.Outsourced": "No",
        "SupportInfo.1.Type": "Network",
        "SystemInfo.1.BootTime": "",
        "SystemInfo.1.PrimaryTelephone": "",
        "SystemInfo.1.PrimaryUser": "",
        "SystemInfo.1.SysLocation": "",
        "SystemInfo.1.SysTime": "Thu Sep  5 12:38:05 2019",
        "ThermalConfig.1.CriticalEventGenerationInterval": 30,
        "ThermalConfig.1.EventGenerationInterval": 30,
        "ThermalConfig.1.FreshAirCompliantConfiguration": "Yes",
        "ThermalConfig.1.MaxCFM": 0,
        "ThermalConfig.1.ValidFanConfiguration": "NotApplicable",
        "ThermalHistorical.1.IntervalInSeconds": 0,
        "ThermalSettings.1.AirExhaustTempSupport": "Not Supported",
        "ThermalSettings.1.AirTemperatureRiseLimit": "NO LIMIT",
        "ThermalSettings.1.AirTemperatureRiseLimitSupport": "Not Supported",
        "ThermalSettings.1.CurrentSystemProfileValue": "",
        "ThermalSettings.1.FanSpeedHighOffsetVal": 75,
        "ThermalSettings.1.FanSpeedLowOffsetVal": 25,
        "ThermalSettings.1.FanSpeedMaxOffsetVal": 100,
        "ThermalSettings.1.FanSpeedMediumOffsetVal": 50,
        "ThermalSettings.1.FanSpeedOffset": "Off",
        "ThermalSettings.1.MFSMaximumLimit": 100,
        "ThermalSettings.1.MFSMinimumLimit": 0,
        "ThermalSettings.1.MaximumPCIeInletTemperatureLimit": "55",
        "ThermalSettings.1.MaximumPCIeInletTemperatureLimitSupport": "Not Supported",
        "ThermalSettings.1.MinimumFanSpeed": 255,
        "ThermalSettings.1.PCIeSlotLFMSupport": "Not Supported",
        "ThermalSettings.1.SetAirTemperatureRiseLimit": "Disabled",
        "ThermalSettings.1.SetMaximumExhaustTemperatureLimit": "Disabled",
        "ThermalSettings.1.SystemCFMSupport": "Not Supported",
        "ThermalSettings.1.SystemExhaustTemperature": 0,
        "ThermalSettings.1.SystemInletTemperature": 15,
        "ThermalSettings.1.SystemInletTemperatureSupportLimitPerConfiguration": 40,
        "ThermalSettings.1.TargetExhaustTemperatureLimit": 70,
        "ThermalSettings.1.ThermalProfile": "Default Thermal Profile Settings",
        "USBFront.1.Enable": "Not Applicable",
        "WarrantyInfo.1.Cost": "0",
        "WarrantyInfo.1.Duration": "0",
        "WarrantyInfo.1.EndDate": "",
        "WarrantyInfo.1.UnitType": "Days"
    },
    "Description": "This schema provides the oem attributes",
    "Id": "SystemAttributes",
    "Name": "OEMAttributeRegistry"
}