{
    "@odata.context": "/redfish/v1/$metadata#HpeServerConfigLock.HpeServerConfigLock",
    "@odata.etag": "W/\"3643D683E7449B9B9BC735AC4F1ABEE6\"",
    "@odata.id": "/redfish/v1/systems/1/bios/serverconfiglock/settings/",
    "@odata.type": "#HpeServerConfigLock.v1_0_0.HpeServerConfigLock",
    "Id": "settings",
    "Name": "Server Configuration Lock Pending Settings",
    "NewServerConfigLockPassword": null,
    "ServerConfigLockChallenge": null,
    "ServerConfigLockDisable": null,
    "ServerConfigLockExcludeCpus": null,
    "ServerConfigLockExcludeDimms": null,
    "ServerConfigLockExcludeFwRevs": null,
    "ServerConfigLockExcludePciSlots": null,
    "ServerConfigLockExcludeSecurity": null,
    "ServerConfigLockLogStored": "False",
    "ServerConfigLockPassword": null,
    "ServerConfigLockState": "Disabled",
    "ServerConfigLockTamperHalt": null,
    "ServerConfigLockTransport": null
}