{
    "@odata.context": "/redfish/v1/$metadata#JsonSchemaFile.JsonSchemaFile",
    "@odata.type": "#JsonSchemaFile.JsonSchemaFile",
    "@odata.id": "/redfish/v1/JsonSchemas/VirtualMedia",
    "Id": "VirtualMedia",
    "Name": "VirtualMedia Schema File",
    "Description": "VirtualMedia Schema File Location",
    "Languages": [
        "en"
    ],
    "Schema": "VirtualMedia",
    "Location": [
        {
            "Language": "en",
            "Uri": "/schemas/v1/VirtualMedia.json"
        }
    ],
    "Oem": {}
}